{"v":"5.2.0","fr":25,"ip":0,"op":125,"w":750,"h":332,"nm":"组合列表banner","ddd":0,"assets":[{"id":"image_0","w":140,"h":179,"u":"images/","p":"img_portfolio_0.png","e":0},{"id":"image_1","w":156,"h":189,"u":"images/","p":"img_portfolio_1.png","e":0},{"id":"image_2","w":199,"h":153,"u":"images/","p":"img_portfolio_2.png","e":0},{"id":"image_3","w":62,"h":24,"u":"images/","p":"img_portfolio_3.png","e":0},{"id":"image_4","w":212,"h":82,"u":"images/","p":"img_portfolio_4.png","e":0},{"id":"image_5","w":69,"h":54,"u":"images/","p":"img_portfolio_5.png","e":0},{"id":"image_6","w":257,"h":197,"u":"images/","p":"img_portfolio_6.png","e":0},{"id":"image_7","w":257,"h":197,"u":"images/","p":"img_portfolio_7.png","e":0},{"id":"image_8","w":750,"h":332,"u":"images/","p":"img_portfolio_8.png","e":0},{"id":"comp_0","layers":[{"ddd":0,"ind":1,"ty":2,"nm":"组合实验室","refId":"image_0","sr":1,"ks":{"o":{"a":1,"k":[{"i":{"x":[0.833],"y":[0.833]},"o":{"x":[0.167],"y":[0.167]},"n":["0p833_0p833_0p167_0p167"],"t":0,"s":[0],"e":[100]},{"i":{"x":[0.833],"y":[0.833]},"o":{"x":[0.167],"y":[0.167]},"n":["0p833_0p833_0p167_0p167"],"t":17,"s":[100],"e":[100]},{"i":{"x":[0.667],"y":[1]},"o":{"x":[0.167],"y":[0]},"n":["0p667_1_0p167_0"],"t":32,"s":[100],"e":[100]},{"i":{"x":[0.833],"y":[1]},"o":{"x":[0.333],"y":[0]},"n":["0p833_1_0p333_0"],"t":49,"s":[100],"e":[100]},{"i":{"x":[0.833],"y":[0.833]},"o":{"x":[0.167],"y":[0.167]},"n":["0p833_0p833_0p167_0p167"],"t":65,"s":[100],"e":[100]},{"i":{"x":[0.833],"y":[0.833]},"o":{"x":[0.167],"y":[0.167]},"n":["0p833_0p833_0p167_0p167"],"t":81,"s":[100],"e":[100]},{"i":{"x":[0.833],"y":[0.833]},"o":{"x":[0.167],"y":[0.167]},"n":["0p833_0p833_0p167_0p167"],"t":106,"s":[100],"e":[0]},{"t":115}],"ix":11},"r":{"a":0,"k":0,"ix":10},"p":{"a":1,"k":[{"i":{"x":0.667,"y":1},"o":{"x":0.333,"y":0},"n":"0p667_1_0p333_0","t":0,"s":[272.68,225.822,0],"e":[272.68,275.822,0],"to":[0,8.33333301544189,0],"ti":[0,0,0]},{"i":{"x":0.667,"y":1},"o":{"x":0.333,"y":0},"n":"0p667_1_0p333_0","t":17,"s":[272.68,275.822,0],"e":[272.68,225.822,0],"to":[0,0,0],"ti":[0,0,0]},{"i":{"x":0.667,"y":1},"o":{"x":0.333,"y":0},"n":"0p667_1_0p333_0","t":32,"s":[272.68,225.822,0],"e":[272.68,275.822,0],"to":[0,0,0],"ti":[0,0,0]},{"i":{"x":0.667,"y":1},"o":{"x":0.333,"y":0},"n":"0p667_1_0p333_0","t":49,"s":[272.68,275.822,0],"e":[272.68,225.822,0],"to":[0,0,0],"ti":[0,0,0]},{"i":{"x":0.667,"y":1},"o":{"x":0.333,"y":0},"n":"0p667_1_0p333_0","t":65,"s":[272.68,225.822,0],"e":[272.68,275.822,0],"to":[0,0,0],"ti":[0,-8.33333301544189,0]},{"i":{"x":0.667,"y":0.667},"o":{"x":0.333,"y":0.333},"n":"0p667_0p667_0p333_0p333","t":81,"s":[272.68,275.822,0],"e":[272.68,275.822,0],"to":[0,0,0],"ti":[0,0,0]},{"i":{"x":0.667,"y":1},"o":{"x":0.333,"y":0},"n":"0p667_1_0p333_0","t":106,"s":[272.68,275.822,0],"e":[272.68,225.822,0],"to":[0,-8.33333301544189,0],"ti":[0,8.33333301544189,0]},{"t":115}],"ix":2},"a":{"a":1,"k":[{"i":{"x":0.833,"y":0.833},"o":{"x":0.167,"y":0.167},"n":"0p833_0p833_0p167_0p167","t":0,"s":[69.57,89.021,0],"e":[69.57,89.021,0],"to":[0,0,0],"ti":[0,0,0]},{"i":{"x":0.833,"y":0.833},"o":{"x":0.167,"y":0.167},"n":"0p833_0p833_0p167_0p167","t":17,"s":[69.57,89.021,0],"e":[69.57,89.021,0],"to":[0,0,0],"ti":[0,0,0]},{"i":{"x":0.667,"y":0.667},"o":{"x":0.167,"y":0.167},"n":"0p667_0p667_0p167_0p167","t":32,"s":[69.57,89.021,0],"e":[69.57,89.021,0],"to":[0,0,0],"ti":[0,0,0]},{"i":{"x":0.833,"y":0.833},"o":{"x":0.333,"y":0.333},"n":"0p833_0p833_0p333_0p333","t":49,"s":[69.57,89.021,0],"e":[69.57,89.021,0],"to":[0,0,0],"ti":[0,0,0]},{"i":{"x":0.833,"y":0.833},"o":{"x":0.167,"y":0.167},"n":"0p833_0p833_0p167_0p167","t":65,"s":[69.57,89.021,0],"e":[69.57,89.021,0],"to":[0,0,0],"ti":[0,0,0]},{"i":{"x":0.833,"y":0.833},"o":{"x":0.167,"y":0.167},"n":"0p833_0p833_0p167_0p167","t":81,"s":[69.57,89.021,0],"e":[69.57,89.021,0],"to":[0,0,0],"ti":[0,0,0]},{"i":{"x":0.833,"y":0.833},"o":{"x":0.167,"y":0.167},"n":"0p833_0p833_0p167_0p167","t":106,"s":[69.57,89.021,0],"e":[69.57,89.021,0],"to":[0,0,0],"ti":[0,0,0]},{"t":115}],"ix":1},"s":{"a":0,"k":[100,100,100],"ix":6}},"ao":0,"ip":0,"op":750,"st":0,"bm":0},{"ddd":0,"ind":2,"ty":2,"nm":"人工操作台","refId":"image_1","sr":1,"ks":{"o":{"a":0,"k":100,"ix":11},"r":{"a":0,"k":0,"ix":10},"p":{"a":0,"k":[233.314,473.483,0],"ix":2},"a":{"a":0,"k":[77.867,94.099,0],"ix":1},"s":{"a":0,"k":[100,100,100],"ix":6}},"ao":0,"ip":0,"op":750,"st":0,"bm":0},{"ddd":0,"ind":3,"ty":2,"nm":"组合","refId":"image_2","sr":1,"ks":{"o":{"a":0,"k":100,"ix":11},"r":{"a":0,"k":0,"ix":10},"p":{"a":0,"k":[423.048,302.317,0],"ix":2},"a":{"a":0,"k":[99.031,76.137,0],"ix":1},"s":{"a":1,"k":[{"i":{"x":[0.833,0.833,0.833],"y":[0.833,0.833,0.833]},"o":{"x":[0.167,0.167,0.167],"y":[0.167,0.167,0.167]},"n":["0p833_0p833_0p167_0p167","0p833_0p833_0p167_0p167","0p833_0p833_0p167_0p167"],"t":7,"s":[0,0,100],"e":[100,100,100]},{"t":15}],"ix":6}},"ao":0,"ip":0,"op":750,"st":0,"bm":0},{"ddd":0,"ind":4,"ty":2,"nm":"线条","refId":"image_3","sr":1,"ks":{"o":{"a":1,"k":[{"i":{"x":[0.833],"y":[0.833]},"o":{"x":[0.167],"y":[0.167]},"n":["0p833_0p833_0p167_0p167"],"t":0,"s":[0],"e":[100]},{"t":15}],"ix":11},"r":{"a":0,"k":0,"ix":10},"p":{"a":0,"k":[363.051,238.101,0],"ix":2},"a":{"a":0,"k":[30.809,11.644,0],"ix":1},"s":{"a":0,"k":[100,100,100],"ix":6}},"ao":0,"ip":0,"op":750,"st":0,"bm":0},{"ddd":0,"ind":5,"ty":2,"nm":"线条","refId":"image_4","sr":1,"ks":{"o":{"a":1,"k":[{"i":{"x":[0.833],"y":[0.833]},"o":{"x":[0.167],"y":[0.167]},"n":["0p833_0p833_0p167_0p167"],"t":0,"s":[0],"e":[100]},{"t":15}],"ix":11},"r":{"a":0,"k":0,"ix":10},"p":{"a":0,"k":[387.451,529.142,0],"ix":2},"a":{"a":0,"k":[105.792,40.556,0],"ix":1},"s":{"a":0,"k":[100,100,100],"ix":6}},"ao":0,"ip":0,"op":750,"st":0,"bm":0},{"ddd":0,"ind":6,"ty":2,"nm":"小方块","refId":"image_5","sr":1,"ks":{"o":{"a":0,"k":100,"ix":11},"r":{"a":0,"k":0,"ix":10},"p":{"a":0,"k":[543.115,498.036,0],"ix":2},"a":{"a":0,"k":[34.496,26.559,0],"ix":1},"s":{"a":1,"k":[{"i":{"x":[0.833,0.833,0.833],"y":[0.833,0.833,0.833]},"o":{"x":[0.167,0.167,0.167],"y":[0.167,0.167,0.167]},"n":["0p833_0p833_0p167_0p167","0p833_0p833_0p167_0p167","0p833_0p833_0p167_0p167"],"t":0,"s":[0,0,100],"e":[100,100,100]},{"t":10}],"ix":6}},"ao":0,"ip":0,"op":750,"st":0,"bm":0},{"ddd":0,"ind":7,"ty":2,"nm":"方块2","refId":"image_6","sr":1,"ks":{"o":{"a":0,"k":100,"ix":11},"r":{"a":0,"k":0,"ix":10},"p":{"a":0,"k":[423.048,345.452,0],"ix":2},"a":{"a":0,"k":[128.085,98.457,0],"ix":1},"s":{"a":1,"k":[{"i":{"x":[0.833,0.833,0.833],"y":[0.833,0.833,0.833]},"o":{"x":[0.167,0.167,0.167],"y":[0.167,0.167,0.167]},"n":["0p833_0p833_0p167_0p167","0p833_0p833_0p167_0p167","0p833_0p833_0p167_0p167"],"t":4,"s":[0,0,100],"e":[100,100,100]},{"t":13}],"ix":6}},"ao":0,"ip":0,"op":750,"st":0,"bm":0},{"ddd":0,"ind":8,"ty":2,"nm":"方块3","refId":"image_7","sr":1,"ks":{"o":{"a":0,"k":100,"ix":11},"r":{"a":0,"k":0,"ix":10},"p":{"a":0,"k":[423.048,416.452,0],"ix":2},"a":{"a":0,"k":[128.085,98.456,0],"ix":1},"s":{"a":1,"k":[{"i":{"x":[0.833,0.833,0.833],"y":[0.833,0.833,0.833]},"o":{"x":[0.167,0.167,0.167],"y":[0.167,0.167,0.167]},"n":["0p833_0p833_0p167_0p167","0p833_0p833_0p167_0p167","0p833_0p833_0p167_0p167"],"t":0,"s":[0,0,100],"e":[100,100,100]},{"t":8}],"ix":6}},"ao":0,"ip":0,"op":750,"st":0,"bm":0}]}],"layers":[{"ddd":0,"ind":1,"ty":0,"nm":"组合列表","refId":"comp_0","sr":1,"ks":{"o":{"a":0,"k":100,"ix":11},"r":{"a":0,"k":0,"ix":10},"p":{"a":0,"k":[600,139,0],"ix":2},"a":{"a":0,"k":[375,375,0],"ix":1},"s":{"a":0,"k":[52.8,52.8,100],"ix":6}},"ao":0,"w":750,"h":750,"ip":0,"op":750,"st":0,"bm":0},{"ddd":0,"ind":4,"ty":2,"nm":"矩形@2x.png","cl":"png","refId":"image_8","sr":1,"ks":{"o":{"a":0,"k":100,"ix":11},"r":{"a":0,"k":0,"ix":10},"p":{"a":0,"k":[375,166,0],"ix":2},"a":{"a":0,"k":[375,166,0],"ix":1},"s":{"a":0,"k":[100,100,100],"ix":6}},"ao":0,"ip":0,"op":750,"st":0,"bm":0}],"markers":[]}